Workbook

Sheet Portfolio Dashboard
B2: Portfolio Dashboard
B3: Meridian Digital Consulting · 6 active projects · period ending 31 Aug 2026 (month 8 of 12). Every figure computes from the data tabs — change an input and this refreshes.
B5: PORTFOLIO HEADLINE
B6: Portfolio revenue | C6: =SUM(Projects!E6:E11) -> 2215000
B7: Cost budget | C7: =SUM(Projects!F6:F11) -> 1640000
B8: Actual cost to date | C8: =SUM(Actuals!P6:P11) -> 1448625.9
B9: Committed cost | C9: =SUM(Committed!D6:D11) -> 177000
B10: Forecast cost (EAC) | C10: =SUM(I17:I22) -> 1868477.3
B11: Planned margin | C11: =(C6-C7)/C6 -> 0.25959368
B12: Forecast margin | C12: =(C6-C10)/C6 -> 0.15644366
B13: Margin erosion | C13: =C11-C12 -> 0.10315002
B15: BY PROJECT — computed status vs what the PM reported
B16: Project | C16: PM | D16: Revenue | E16: Cost Budget | F16: YTD Budget | G16: Actual | H16: Committed | I16: Forecast (EAC) | J16: Variance | K16: Var % | L16: Margin % | M16: COMPUTED RAG | N16: PM SAID | O16: FLAG
B17: =Projects!C6 -> Retail Bank Mobile App Rollout | C17: =Projects!I6 -> G. Liu | D17: =Projects!E6 -> 485000 | E17: =Projects!F6 -> 352000 | F17: =SUM(Budget!D6:K6) -> 352000.02 | G17: =Actuals!P6 -> 357727.2 | H17: =Committed!D6 -> 18500 | I17: =G17+H17+SUM(Budget!L6:O6) -> 376227.2 | J17: =E17-I17 -> -24227.2 | K17: =IF(E17=0,0,J17/E17) -> -0.068827273 | L17: =IF(D17=0,0,(D17-I17)/D17) -> 0.22427381 | M17: =IF(K17>=-0.02,"GREEN",IF(K17>=-0.1,"AMBER","RED")) -> AMBER | N17: ='PM Reported RAG'!D6 -> Green | O17: =IF(AND(N17="Green",M17<>"GREEN"),"UNDER-REPORTED",IF(M17<>UPPER(N17),"mismatch","")) -> UNDER-REPORTED
B18: =Projects!C7 -> Wealth Platform Data Migration | C18: =Projects!I7 -> G. Liu | D18: =Projects!E7 -> 312000 | E18: =Projects!F7 -> 236000 | F18: =SUM(Budget!D7:K7) -> 219268.19 | G18: =Actuals!P7 -> 206114.26 | H18: =Committed!D7 -> 9200 | I18: =G18+H18+SUM(Budget!L7:O7) -> 232046.09 | J18: =E18-I18 -> 3953.91 | K18: =IF(E18=0,0,J18/E18) -> 0.016753856 | L18: =IF(D18=0,0,(D18-I18)/D18) -> 0.25626253 | M18: =IF(K18>=-0.02,"GREEN",IF(K18>=-0.1,"AMBER","RED")) -> GREEN | N18: ='PM Reported RAG'!D7 -> Amber | O18: =IF(AND(N18="Green",M18<>"GREEN"),"UNDER-REPORTED",IF(M18<>UPPER(N18),"mismatch","")) -> mismatch
B19: =Projects!C8 -> Insurance Claims Automation | C19: =Projects!I8 -> O. Haddad | D19: =Projects!E8 -> 640000 | E19: =Projects!F8 -> 470000 | F19: =SUM(Budget!D8:K8) -> 371078.71 | G19: =Actuals!P8 -> 381081.15 | H19: =Committed!D8 -> 86500 | I19: =G19+H19+SUM(Budget!L8:O8) -> 566502.43 | J19: =E19-I19 -> -96502.43 | K19: =IF(E19=0,0,J19/E19) -> -0.20532432 | L19: =IF(D19=0,0,(D19-I19)/D19) -> 0.11483995 | M19: =IF(K19>=-0.02,"GREEN",IF(K19>=-0.1,"AMBER","RED")) -> RED | N19: ='PM Reported RAG'!D8 -> Green | O19: =IF(AND(N19="Green",M19<>"GREEN"),"UNDER-REPORTED",IF(M19<>UPPER(N19),"mismatch","")) -> UNDER-REPORTED
B20: =Projects!C9 -> Core Banking API Layer | C20: =Projects!I9 -> O. Haddad | D20: =Projects!E9 -> 228000 | E20: =Projects!F9 -> 171000 | F20: =SUM(Budget!D9:K9) -> 139269.43 | G20: =Actuals!P9 -> 151410.48 | H20: =Committed!D9 -> 21000 | I20: =G20+H20+SUM(Budget!L9:O9) -> 204141.07 | J20: =E20-I20 -> -33141.07 | K20: =IF(E20=0,0,J20/E20) -> -0.19380743 | L20: =IF(D20=0,0,(D20-I20)/D20) -> 0.10464443 | M20: =IF(K20>=-0.02,"GREEN",IF(K20>=-0.1,"AMBER","RED")) -> RED | N20: ='PM Reported RAG'!D9 -> Green | O20: =IF(AND(N20="Green",M20<>"GREEN"),"UNDER-REPORTED",IF(M20<>UPPER(N20),"mismatch","")) -> UNDER-REPORTED
B21: =Projects!C10 -> Regulatory Reporting Dashboard | C21: =Projects!I10 -> G. Liu | D21: =Projects!E10 -> 156000 | E21: =Projects!F10 -> 112000 | F21: =SUM(Budget!D10:K10) -> 112000 | G21: =Actuals!P10 -> 112702.04 | H21: =Committed!D10 -> 0 | I21: =G21+H21+SUM(Budget!L10:O10) -> 112702.04 | J21: =E21-I21 -> -702.04 | K21: =IF(E21=0,0,J21/E21) -> -0.0062682143 | L21: =IF(D21=0,0,(D21-I21)/D21) -> 0.27755103 | M21: =IF(K21>=-0.02,"GREEN",IF(K21>=-0.1,"AMBER","RED")) -> GREEN | N21: ='PM Reported RAG'!D10 -> Green | O21: =IF(AND(N21="Green",M21<>"GREEN"),"UNDER-REPORTED",IF(M21<>UPPER(N21),"mismatch",""))
B22: =Projects!C11 -> Payments Fraud Model Uplift | C22: =Projects!I11 -> O. Haddad | D22: =Projects!E11 -> 394000 | E22: =Projects!F11 -> 299000 | F22: =SUM(Budget!D11:K11) -> 203532.25 | G22: =Actuals!P11 -> 239590.73 | H22: =Committed!D11 -> 41800 | I22: =G22+H22+SUM(Budget!L11:O11) -> 376858.47 | J22: =E22-I22 -> -77858.47 | K22: =IF(E22=0,0,J22/E22) -> -0.26039622 | L22: =IF(D22=0,0,(D22-I22)/D22) -> 0.043506421 | M22: =IF(K22>=-0.02,"GREEN",IF(K22>=-0.1,"AMBER","RED")) -> RED | N22: ='PM Reported RAG'!D11 -> Amber | O22: =IF(AND(N22="Green",M22<>"GREEN"),"UNDER-REPORTED",IF(M22<>UPPER(N22),"mismatch","")) -> mismatch
B23: PORTFOLIO | D23: =SUM(D17:D22) -> 2215000 | E23: =SUM(E17:E22) -> 1640000 | F23: =SUM(F17:F22) -> 1397148.6 | G23: =SUM(G17:G22) -> 1448625.9 | H23: =SUM(H17:H22) -> 177000 | I23: =SUM(I17:I22) -> 1868477.3 | J23: =SUM(J17:J22) -> -228477.3 | K23: =J23/E23 -> -0.13931543 | L23: =(D23-I23)/D23 -> 0.15644366
B26: DELIVERY HEALTH
B27: Milestones at risk | F27: =COUNTIF(Milestones!H6:H25,"At Risk") -> 7
B28: Milestones met late | F28: =COUNTIF(Milestones!H6:H25,"Met (late)") -> 7
B29: Worst milestone slip (days) | F29: =MAX(Milestones!I6:I25) -> 42
B30: Benefits Red or Dropped | F30: =COUNTIF(Benefits!G6:G12,"Red") -> 1
B31: Projects PM-reported Green but computed worse | F31: =COUNTIF(O17:O22,"UNDER-REPORTED") -> 3

Sheet Projects
B2: Project Portfolio — master
B3: 6 client projects · revenue, cost budget, PM. All dashboard figures compute from this data.
B5: Project ID | C5: Project Name | D5: Billing Type | E5: Contract Value (Revenue) | F5: Cost Budget | G5: Start | H5: End | I5: Project Manager
B6: PRJ-OP-201 | C6: Retail Bank Mobile App Rollout | D6: Fixed Price | E6: 485000 | F6: 352000 | G6: 2026-01-12 | H6: 2026-08-28 | I6: G. Liu
B7: PRJ-OP-202 | C7: Wealth Platform Data Migration | D7: Time & Material | E7: 312000 | F7: 236000 | G7: 2026-02-02 | H7: 2026-09-30 | I7: G. Liu
B8: PRJ-OP-203 | C8: Insurance Claims Automation | D8: Fixed Price | E8: 640000 | F8: 470000 | G8: 2026-01-05 | H8: 2026-11-20 | I8: O. Haddad
B9: PRJ-OP-204 | C9: Core Banking API Layer | D9: Time & Material | E9: 228000 | F9: 171000 | G9: 2026-03-16 | H9: 2026-10-15 | I9: O. Haddad
B10: PRJ-OP-205 | C10: Regulatory Reporting Dashboard | D10: Fixed Price | E10: 156000 | F10: 112000 | G10: 2026-04-01 | H10: 2026-08-14 | I10: G. Liu
B11: PRJ-OP-206 | C11: Payments Fraud Model Uplift | D11: Time & Material | E11: 394000 | F11: 299000 | G11: 2026-02-23 | H11: 2026-12-04 | I11: O. Haddad

Sheet Budget
B2: Cost Budget — by project by month
B3: Baselined plan. Total column drives the dashboard.
B5: Project ID | C5: Project Name | D5: Jan | E5: Feb | F5: Mar | G5: Apr | H5: May | I5: Jun | J5: Jul | K5: Aug | L5: Sep | M5: Oct | N5: Nov | O5: Dec | P5: Total Cost Budget
B6: PRJ-OP-201 | C6: Retail Bank Mobile App Rollout | D6: 24955.95 | E6: 40360.81 | F6: 52151.17 | G6: 58532.08 | H6: 58532.08 | I6: 52151.17 | J6: 40360.81 | K6: 24955.95 | L6: 0 | M6: 0 | N6: 0 | O6: 0 | P6: 352000.02
B7: PRJ-OP-202 | C7: Wealth Platform Data Migration | D7: 0 | E7: 16731.83 | F7: 27060.09 | G7: 34964.99 | H7: 39243.1 | I7: 39243.1 | J7: 34964.99 | K7: 27060.09 | L7: 16731.83 | M7: 0 | N7: 0 | O7: 0 | P7: 236000.02
B8: PRJ-OP-203 | C8: Insurance Claims Automation | D8: 22085.61 | E8: 33440.17 | F8: 43395.5 | G8: 51145.07 | H8: 56061.05 | I8: 57745.19 | J8: 56061.05 | K8: 51145.07 | L8: 43395.5 | M8: 33440.17 | N8: 22085.61 | O8: 0 | P8: 469999.99
B9: PRJ-OP-204 | C9: Core Banking API Layer | D9: 0 | E9: 0 | F9: 12123.49 | G9: 19607.1 | H9: 25334.8 | I9: 28434.62 | J9: 28434.62 | K9: 25334.8 | L9: 19607.1 | M9: 12123.49 | N9: 0 | O9: 0 | P9: 171000.02
B10: PRJ-OP-205 | C10: Regulatory Reporting Dashboard | D10: 0 | E10: 0 | F10: 0 | G10: 15088.36 | H10: 25898.11 | I10: 30027.06 | J10: 25898.11 | K10: 15088.36 | L10: 0 | M10: 0 | N10: 0 | O10: 0 | P10: 112000
B11: PRJ-OP-206 | C11: Payments Fraud Model Uplift | D11: 0 | E11: 14050.21 | F11: 21273.64 | G11: 27606.92 | H11: 32536.97 | I11: 35664.37 | J11: 36735.77 | K11: 35664.37 | L11: 32536.97 | M11: 27606.92 | N11: 21273.64 | O11: 14050.21 | P11: 298999.99

Sheet Actuals
B2: Actual Cost — by project by month
B3: Posted actuals through August (month 8 of 12). Sep–Dec are zero — not yet incurred.
B5: Project ID | C5: Project Name | D5: Jan | E5: Feb | F5: Mar | G5: Apr | H5: May | I5: Jun | J5: Jul | K5: Aug | L5: Sep | M5: Oct | N5: Nov | O5: Dec | P5: Total Actual
B6: PRJ-OP-201 | C6: Retail Bank Mobile App Rollout | D6: 26216.47 | E6: 40451.32 | F6: 51813.77 | G6: 61628.47 | H6: 57404.54 | I6: 53067.79 | J6: 41406.37 | K6: 25738.47 | L6: 0 | M6: 0 | N6: 0 | O6: 0 | P6: 357727.2
B7: PRJ-OP-202 | C7: Wealth Platform Data Migration | D7: 0 | E7: 15170.32 | F7: 25768.81 | G7: 32869.13 | H7: 38183.74 | I7: 35148.67 | J7: 34369.69 | K7: 24603.9 | L7: 0 | M7: 0 | N7: 0 | O7: 0 | P7: 206114.26
B8: PRJ-OP-203 | C8: Insurance Claims Automation | D8: 23461 | E8: 34468.57 | F8: 46197.83 | G8: 51008.82 | H8: 56712.07 | I8: 57022.21 | J8: 59352.29 | K8: 52858.36 | L8: 0 | M8: 0 | N8: 0 | O8: 0 | P8: 381081.15
B9: PRJ-OP-204 | C9: Core Banking API Layer | D9: 0 | E9: 0 | F9: 13060.06 | G9: 21092.87 | H9: 26943.19 | I9: 30615.97 | J9: 31752.13 | K9: 27946.26 | L9: 0 | M9: 0 | N9: 0 | O9: 0 | P9: 151410.48
B10: PRJ-OP-205 | C10: Regulatory Reporting Dashboard | D10: 0 | E10: 0 | F10: 0 | G10: 15242.59 | H10: 24552.8 | I10: 30735.97 | J10: 26875.15 | K10: 15295.53 | L10: 0 | M10: 0 | N10: 0 | O10: 0 | P10: 112702.04
B11: PRJ-OP-206 | C11: Payments Fraud Model Uplift | D11: 0 | E11: 16982.35 | F11: 25980.85 | G11: 31256.58 | H11: 38244.8 | I11: 40313.62 | J11: 44568.76 | K11: 42243.77 | L11: 0 | M11: 0 | N11: 0 | O11: 0 | P11: 239590.73

Sheet Committed
B2: Committed Cost — raised, not yet in actuals
B3: Contracted extensions and open POs. THIS is what turns a Green project Red.
B5: Project ID | C5: Project Name | D5: Committed Cost | E5: Description
B6: PRJ-OP-201 | C6: Retail Bank Mobile App Rollout | D6: 18500 | E6: Hypercare support extension
B7: PRJ-OP-202 | C7: Wealth Platform Data Migration | D7: 9200 | E7: Contract data engineer Sep-Oct
B8: PRJ-OP-203 | C8: Insurance Claims Automation | D8: 86500 | E8: 2 contractors extended to Nov + licence uplift
B9: PRJ-OP-204 | C9: Core Banking API Layer | D9: 21000 | E9: API gateway licences
B10: PRJ-OP-205 | C10: Regulatory Reporting Dashboard | D10: 0 | E10: None
B11: PRJ-OP-206 | C11: Payments Fraud Model Uplift | D11: 41800 | E11: ML specialist extension to Dec
C12: TOTAL | D12: =SUM(D6:D11) -> 177000

Sheet Milestones
B2: Milestone Tracker — all projects
B3: Baseline vs forecast vs actual. Slippage is computed, not typed.
B5: Project ID | C5: Milestone ID | D5: Milestone | E5: Baseline Date | F5: Forecast Date | G5: Actual Date | H5: Status | I5: Slip (days)
B6: PRJ-OP-201 | C6: M1 | D6: Design sign-off | E6: 2026-02-20 | F6: 2026-02-20 | G6: 2026-02-20 | H6: Met | I6: =IF(OR(E6="",F6=""),"",DATEDIF(DATEVALUE(E6),DATEVALUE(F6),"d")) -> 0
B7: PRJ-OP-201 | C7: M2 | D7: Build complete | E7: 2026-05-29 | F7: 2026-06-05 | G7: 2026-06-05 | H7: Met (late) | I7: =IF(OR(E7="",F7=""),"",DATEDIF(DATEVALUE(E7),DATEVALUE(F7),"d")) -> 7
B8: PRJ-OP-201 | C8: M3 | D8: UAT sign-off | E8: 2026-07-24 | F8: 2026-07-31 | G8: 2026-07-31 | H8: Met (late) | I8: =IF(OR(E8="",F8=""),"",DATEDIF(DATEVALUE(E8),DATEVALUE(F8),"d")) -> 7
B9: PRJ-OP-201 | C9: M4 | D9: Go-live | E9: 2026-08-28 | F9: 2026-08-28 | H9: On Track | I9: =IF(OR(E9="",F9=""),"",DATEDIF(DATEVALUE(E9),DATEVALUE(F9),"d")) -> 0
B10: PRJ-OP-202 | C10: M1 | D10: Data mapping approved | E10: 2026-03-13 | F10: 2026-03-27 | G10: 2026-03-27 | H10: Met (late) | I10: =IF(OR(E10="",F10=""),"",DATEDIF(DATEVALUE(E10),DATEVALUE(F10),"d")) -> 14
B11: PRJ-OP-202 | C11: M2 | D11: Trial migration | E11: 2026-06-12 | F11: 2026-07-10 | G11: 2026-07-10 | H11: Met (late) | I11: =IF(OR(E11="",F11=""),"",DATEDIF(DATEVALUE(E11),DATEVALUE(F11),"d")) -> 28
B12: PRJ-OP-202 | C12: M3 | D12: Cutover | E12: 2026-09-30 | F12: 2026-10-16 | H12: At Risk | I12: =IF(OR(E12="",F12=""),"",DATEDIF(DATEVALUE(E12),DATEVALUE(F12),"d")) -> 16
B13: PRJ-OP-203 | C13: M1 | D13: Requirements baselined | E13: 2026-02-13 | F13: 2026-02-13 | G13: 2026-02-13 | H13: Met | I13: =IF(OR(E13="",F13=""),"",DATEDIF(DATEVALUE(E13),DATEVALUE(F13),"d")) -> 0
B14: PRJ-OP-203 | C14: M2 | D14: Model build complete | E14: 2026-06-30 | F14: 2026-07-24 | G14: 2026-07-24 | H14: Met (late) | I14: =IF(OR(E14="",F14=""),"",DATEDIF(DATEVALUE(E14),DATEVALUE(F14),"d")) -> 24
B15: PRJ-OP-203 | C15: M3 | D15: UAT sign-off | E15: 2026-09-25 | F15: 2026-10-23 | H15: At Risk | I15: =IF(OR(E15="",F15=""),"",DATEDIF(DATEVALUE(E15),DATEVALUE(F15),"d")) -> 28
B16: PRJ-OP-203 | C16: M4 | D16: Go-live | E16: 2026-11-20 | F16: 2026-12-18 | H16: At Risk | I16: =IF(OR(E16="",F16=""),"",DATEDIF(DATEVALUE(E16),DATEVALUE(F16),"d")) -> 28
B17: PRJ-OP-204 | C17: M1 | D17: API spec approved | E17: 2026-04-17 | F17: 2026-04-17 | G17: 2026-04-17 | H17: Met | I17: =IF(OR(E17="",F17=""),"",DATEDIF(DATEVALUE(E17),DATEVALUE(F17),"d")) -> 0
B18: PRJ-OP-204 | C18: M2 | D18: Integration complete | E18: 2026-08-14 | F18: 2026-08-28 | H18: At Risk | I18: =IF(OR(E18="",F18=""),"",DATEDIF(DATEVALUE(E18),DATEVALUE(F18),"d")) -> 14
B19: PRJ-OP-204 | C19: M3 | D19: Go-live | E19: 2026-10-15 | F19: 2026-10-30 | H19: At Risk | I19: =IF(OR(E19="",F19=""),"",DATEDIF(DATEVALUE(E19),DATEVALUE(F19),"d")) -> 15
B20: PRJ-OP-205 | C20: M1 | D20: Report specs signed | E20: 2026-05-01 | F20: 2026-05-01 | G20: 2026-05-01 | H20: Met | I20: =IF(OR(E20="",F20=""),"",DATEDIF(DATEVALUE(E20),DATEVALUE(F20),"d")) -> 0
B21: PRJ-OP-205 | C21: M2 | D21: Go-live | E21: 2026-08-14 | F21: 2026-08-14 | G21: 2026-08-14 | H21: Met | I21: =IF(OR(E21="",F21=""),"",DATEDIF(DATEVALUE(E21),DATEVALUE(F21),"d")) -> 0
B22: PRJ-OP-206 | C22: M1 | D22: Model design approved | E22: 2026-04-10 | F22: 2026-04-24 | G22: 2026-04-24 | H22: Met (late) | I22: =IF(OR(E22="",F22=""),"",DATEDIF(DATEVALUE(E22),DATEVALUE(F22),"d")) -> 14
B23: PRJ-OP-206 | C23: M2 | D23: Training data ready | E23: 2026-07-03 | F23: 2026-08-07 | G23: 2026-08-07 | H23: Met (late) | I23: =IF(OR(E23="",F23=""),"",DATEDIF(DATEVALUE(E23),DATEVALUE(F23),"d")) -> 35
B24: PRJ-OP-206 | C24: M3 | D24: Model validation | E24: 2026-10-09 | F24: 2026-11-13 | H24: At Risk | I24: =IF(OR(E24="",F24=""),"",DATEDIF(DATEVALUE(E24),DATEVALUE(F24),"d")) -> 35
B25: PRJ-OP-206 | C25: M4 | D25: Production deploy | E25: 2026-12-04 | F25: 2027-01-15 | H25: At Risk | I25: =IF(OR(E25="",F25=""),"",DATEDIF(DATEVALUE(E25),DATEVALUE(F25),"d")) -> 42

Sheet Benefits
B2: Benefits Register
B3: What each project promised vs what it is delivering. One benefit was quietly dropped — find it.
B5: Project ID | C5: Benefit ID | D5: Benefit | E5: Target | F5: Current | G5: RAG | H5: Note
B6: PRJ-OP-201 | C6: BEN-01 | D6: Digital channel adoption +15% | E6: 15% uplift | F6: 12% (tracking) | G6: Amber | H6: Partial - adoption slower in 45+ segment
B7: PRJ-OP-202 | C7: BEN-02 | D7: Legacy platform decommission saving $180K/yr | E7: $180K/yr | F7: $180K/yr | G7: Green | H7: On track - decommission scheduled post-cutover
B8: PRJ-OP-203 | C8: BEN-03 | D8: Claims handling time -30% | E8: 30% reduction | F8: 22% (tracking) | G8: Amber | H8: Automation scope reduced under CR-02
B9: PRJ-OP-204 | C9: BEN-04 | D9: Partner integration time 6wks -> 2wks | E9: 4 wks saved | F9: 4 wks saved | G9: Green | H9: Validated with 2 pilot partners
B10: PRJ-OP-205 | C10: BEN-05 | D10: Regulatory reporting effort -40% | E10: 40% reduction | F10: 41% | G10: Green | H10: Delivered and measured post go-live
B11: PRJ-OP-206 | C11: BEN-06 | D11: Fraud detection recall +8pts | E11: +8 pts | F11: Not yet measurable | G11: Grey | H11: Measurable only after production deploy
B12: PRJ-OP-201 | C12: BEN-07 | D12: Branch call volume -10% | E12: 10% reduction | F12: DROPPED | G12: Red | H12: Quietly de-scoped in month 4; never formally closed or re-baselined

Sheet PM Reported RAG
B2: What the PMs self-report
B3: Compare against the computed RAG on the Portfolio Dashboard. Where they disagree is the PCO's job.
B5: Project ID | C5: PM Reported Overall | D5: PM Reported Cost | E5: PM Reported Schedule | F5: PM Commentary
B6: PRJ-OP-201 | C6: Green | D6: Green | E6: Amber | F6: On track for Aug go-live
B7: PRJ-OP-202 | C7: Amber | D7: Amber | E7: Amber | F7: Cutover date under pressure
B8: PRJ-OP-203 | C8: Green | D8: Green | E8: Green | F8: Reported on budget and on plan
B9: PRJ-OP-204 | C9: Amber | D9: Green | E9: Amber | F9: Integration slipping 2 weeks
B10: PRJ-OP-205 | C10: Green | D10: Green | E10: Green | F10: Delivered
B11: PRJ-OP-206 | C11: Amber | D11: Amber | E11: Red | F11: Model validation at risk

Sheet Resources
B2: Resource Master — the bench
B3: 15 specialists · role, contracted capacity, cost & bill rates.
B5: Resource ID | C5: Resource Name | D5: Role | E5: Resourcing Unit | F5: Capacity (hrs/wk) | G5: Cost Rate | H5: Bill Rate
B6: R-3001 | C6: Amara Okafor | D6: Solution Architect | E6: Architecture | F6: 40 | G6: 95 | H6: 210
B7: R-3002 | C7: Ben Carrow | D7: Senior Developer | E7: Engineering | F7: 40 | G7: 78 | H7: 175
B8: R-3003 | C8: Priya Nair | D8: Senior Developer | E8: Engineering | F8: 40 | G8: 78 | H8: 175
B9: R-3004 | C9: Daniel Kim | D9: Developer | E9: Engineering | F9: 40 | G9: 60 | H9: 140
B10: R-3005 | C10: Sofia Rossi | D10: Developer | E10: Engineering | F10: 40 | G10: 60 | H10: 140
B11: R-3006 | C11: Marcus Bell | D11: QA Lead | E11: Quality | F11: 40 | G11: 68 | H11: 150
B12: R-3007 | C12: Lena Fischer | D12: QA Analyst | E12: Quality | F12: 40 | G12: 52 | H12: 120
B13: R-3008 | C13: Tomas Vega | D13: Data Migration Specialist | E13: Data | F13: 40 | G13: 82 | H13: 185
B14: R-3009 | C14: Hannah Wright | D14: Business Analyst | E14: Advisory | F14: 40 | G14: 70 | H14: 160
B15: R-3010 | C15: Ravi Menon | D15: Business Analyst | E15: Advisory | F15: 32 | G15: 70 | H15: 160
B16: R-3011 | C16: Grace Liu | D16: Project Manager | E16: Delivery | F16: 40 | G16: 88 | H16: 195
B17: R-3012 | C17: Omar Haddad | D17: Scrum Master | E17: Delivery | F17: 40 | G17: 72 | H17: 165
... B20: R-3015 | C20: Yuki Tanaka | D20: UX Designer | E20: Design | F20: 24 | G20: 65 | H20: 150

Sheet Allocations (RAW)
B2: Resource Allocations — raw booking export
B3: 351 rows. Contains 7 data defects — see the Defect Log.
B5: Allocation ID | C5: Resource ID | D5: Resource Name | E5: Role | F5: Project ID | G5: Project Name | H5: Week Starting | I5: Booked Hours | J5: Capacity | K5: Booking Status
B6: AL-70271 | C6: R-3012 | D6: Omar Haddad | E6: Scrum Master | F6: PRJ-OP-206 | G6: Payments Fraud Model Uplift | H6: 2026-07-27 | I6: 32 | J6: 40 | K6: Confirmed
B7: AL-70137 | C7: R-3006 | D7: Marcus Bell | E7: QA Lead | F7: PRJ-OP-201 | G7: Retail Bank Mobile App Rollout | H7: 2026-07-27 | I7: 35 | J7: 40 | K7: Confirmed
B8: AL-70201 | C8: R-3009 | D8: Hannah Wright | E8: Business Analyst | F8: PRJ-OP-202 | G8: Wealth Platform Data Migration | H8: 2026-07-06 | I8: 11 | J8: 40 | K8: Confirmed
B9: AL-70129 | C9: R-3006 | D9: Marcus Bell | E9: QA Lead | F9: PRJ-OP-201 | G9: Retail Bank Mobile App Rollout | H9: 2026-06-29 | I9: 14 | J9: 40 | K9: Confirmed
B10: AL-70183 | C10: R-3008 | D10: Tomas Vega | E10: Data Migration Specialist | F10: PRJ-OP-205 | G10: Regulatory Reporting Dashboard | H10: 2026-08-03 | I10: 20 | J10: 40 | K10: Confirmed
B11: AL-70134 | C11: R-3006 | D11: Marcus Bell | E11: QA Lead | F11: PRJ-OP-204 | G11: Core Banking API Layer | H11: 2026-07-13 | I11: 12 | J11: 40 | K11: Confirmed
B12: AL-70196 | C12: R-3009 | D12: Hannah Wright | E12: Business Analyst | F12: PRJ-OP-201 | G12: Retail Bank Mobile App Rollout | H12: 2026-06-22 | I12: 17 | J12: 40 | K12: Confirmed
B13: AL-70257 | C13: R-3012 | D13: Omar Haddad | E13: Scrum Master | F13: PRJ-OP-205 | G13: Regulatory Reporting Dashboard | H13: 2026-06-08 | I13: 12 | J13: 40 | K13: Confirmed
B14: AL-70029 | C14: R-3002 | D14: Ben Carrow | E14: Senior Developer | F14: PRJ-OP-204 | G14: Core Banking API Layer | H14: 2026-06-15 | I14: 12 | J14: 40 | K14: Confirmed
B15: AL-70215 | C15: R-3010 | D15: Ravi Menon | E15: Business Analyst | F15: PRJ-OP-201 | G15: Retail Bank Mobile App Rollout | H15: 2026-06-15 | I15: 14 | J15: 32 | K15: Confirmed
B16: AL-70081 | C16: R-3004 | D16: Daniel Kim | E16: Developer | F16: PRJ-OP-202 | G16: Wealth Platform Data Migration | H16: 2026-06-29 | I16: 10 | J16: 40 | K16: Confirmed
B17: AL-70236 | C17: R-3011 | D17: Grace Liu | E17: Project Manager | F17: PRJ-OP-205 | G17: Regulatory Reporting Dashboard | H17: 2026-06-22 | I17: 17 | J17: 40 | K17: Confirmed
... B168: AL-70032 | C168: R-3002 | D168: Ben Carrow | E168: Senior Developer | F168: PRJ-OP-202 | G168: Wealth Platform Data Migration | H168: 2026-06-22 | I168: 32 | J168: 40 | K168: Confirmed
B169: AL-70361 | C169: R-3007 | D169: Lena Fischer | E169: QA Analyst | F169: PRJ-OP-205 | G169: Regulatory Reporting Dashboard | H169: 2026-06-22 | J169: 40 | K169: Confirmed
B170: AL-70162 | C170: R-3007 | D170: Lena Fischer | E170: QA Analyst | F170: PRJ-OP-203 | G170: Insurance Claims Automation | H170: 2026-08-10 | I170: 9 | J170: 40 | K170: Confirmed
B171: AL-70031 | C171: R-3002 | D171: Ben Carrow | E171: Senior Developer | F171: PRJ-OP-202 | G171: Wealth Platform Data Migration | H171: 2026-06-15 | I171: 11 | J171: 40 | K171: Confirmed
B172: AL-70211 | C172: R-3009 | D172: Hannah Wright | E172: Business Analyst | F172: PRJ-OP-205 | G172: Regulatory Reporting Dashboard | H172: 2026-08-17 | I172: 15 | J172: 40 | K172: Confirmed
B173: AL-70165 | C173: R-3007 | D173: Lena Fischer | E173: QA Analyst | F173: PRJ-OP-204 | G173: Core Banking API Layer | H173: 2026-08-17 | I173: 13 | J173: 40 | K173: Confirmed
B174: AL-70230 | C174: R-3011 | D174: Grace Liu | E174: Project Manager | F174: PRJ-OP-205 | G174: Regulatory Reporting Dashboard | H174: 2026-06-01 | I174: 17 | J174: 40 | K174: Confirmed
B175: AL-70329 | C175: R-3015 | D175: Yuki Tanaka | E175: UX Designer | F175: PRJ-OP-202 | G175: Wealth Platform Data Migration | H175: 2026-06-29 | I175: 20 | J175: 24 | K175: Confirmed
B176: AL-70133 | C176: R-3006 | D176: Marcus Bell | E176: QA Lead | F176: PRJ-OP-201 | G176: Retail Bank Mobile App Rollout | H176: 2026-07-13 | I176: 15 | J176: 40 | K176: Confirmed
B177: AL-70193 | C177: R-3009 | D177: Hannah Wright | E177: Business Analyst | F177: PRJ-OP-203 | G177: Insurance Claims Automation | H177: 2026-06-15 | I177: 8 | J177: 40 | K177: Confirmed
B178: AL-70228 | C178: R-3010 | D178: Ravi Menon | E178: Business Analyst | F178: PRJ-OP-203 | G178: Insurance Claims Automation | H178: 2026-08-17 | I178: 30 | J178: 32 | K178: Confirmed
B179: AL-70273 | C179: R-3012 | D179: Omar Haddad | E179: Scrum Master | F179: PRJ-OP-206 | G179: Payments Fraud Model Uplift | H179: 2026-08-03 | I179: 17 | J179: 40 | K179: Confirmed
B180: AL-70291 | C180: R-3013 | D180: Nina Patel | E180: Data Engineer | F180: PRJ-OP-201 | G180: Retail Bank Mobile App Rollout | H180: 2026-07-20 | I180: 17 | J180: 40 | K180: Confirmed
B181: AL-70136 | C181: R-3006 | D181: Marcus Bell | E181: QA Lead | F181: PRJ-OP-202 | G181: Wealth Platform Data Migration | H181: 2026-07-20 | I181: 23 | J181: 40 | K181: Confirmed
... B356: AL-70019 | C356: R-3001 | D356: Amara Okafor | E356: Solution Architect | F356: PRJ-OP-203 | G356: Insurance Claims Automation | H356: 2026-08-03 | I356: 19 | J356: 40 | K356: Confirmed

Sheet Time & Expense
B2: Time & Expense — logged hours
B3: Logged vs booked. Billable flag drives revenue recognition.
B5: Entry ID | C5: Resource ID | D5: Resource Name | E5: Project ID | F5: Project Name | G5: Week Starting | H5: Logged Hours | I5: Billable | J5: Approval Status
B6: TE-90125 | C6: R-3007 | D6: Lena Fischer | E6: PRJ-OP-204 | F6: Core Banking API Layer | G6: 2026-08-10 | H6: 11 | I6: Billable | J6: Approved
B7: TE-90106 | C7: R-3003 | D7: Priya Nair | E7: PRJ-OP-202 | F7: Wealth Platform Data Migration | G7: 2026-08-10 | H7: 12 | I7: Non-billable | J7: Approved
B8: TE-90348 | C8: R-3001 | D8: Amara Okafor | E8: PRJ-OP-203 | F8: Insurance Claims Automation | G8: 2026-07-06 | H8: 32 | I8: Billable | J8: Submitted
B9: TE-90248 | C9: R-3005 | D9: Sofia Rossi | E9: PRJ-OP-204 | F9: Core Banking API Layer | G9: 2026-08-17 | H9: 33 | I9: Non-billable | J9: Approved
B10: TE-90269 | C10: R-3005 | D10: Sofia Rossi | E10: PRJ-OP-203 | F10: Insurance Claims Automation | G10: 2026-08-10 | H10: 22 | I10: Billable | J10: Approved
B11: TE-90238 | C11: R-3014 | D11: Jack Thompson | E11: PRJ-OP-205 | F11: Regulatory Reporting Dashboard | G11: 2026-08-03 | H11: 12 | I11: Billable | J11: Approved
B12: TE-90066 | C12: R-3002 | D12: Ben Carrow | E12: PRJ-OP-201 | F12: Retail Bank Mobile App Rollout | G12: 2026-08-10 | H12: 10 | I12: Billable | J12: Approved
B13: TE-90325 | C13: R-3005 | D13: Sofia Rossi | E13: PRJ-OP-206 | F13: Payments Fraud Model Uplift | G13: 2026-08-10 | H13: 18 | I13: Billable | J13: Approved
B14: TE-90336 | C14: R-3001 | D14: Amara Okafor | E14: PRJ-OP-202 | F14: Wealth Platform Data Migration | G14: 2026-06-29 | H14: 10 | I14: Billable | J14: Approved
B15: TE-90078 | C15: R-3013 | D15: Nina Patel | E15: PRJ-OP-203 | F15: Insurance Claims Automation | G15: 2026-06-01 | H15: 13 | I15: Billable | J15: Approved
B16: TE-90247 | C16: R-3007 | D16: Lena Fischer | E16: PRJ-OP-202 | F16: Wealth Platform Data Migration | G16: 2026-07-13 | H16: 34 | I16: Billable | J16: Approved
B17: TE-90060 | C17: R-3015 | D17: Yuki Tanaka | E17: PRJ-OP-205 | F17: Regulatory Reporting Dashboard | G17: 2026-08-10 | H17: 18 | I17: Billable | J17: Approved
... B353: TE-90097 | C353: R-3002 | D353: Ben Carrow | E353: PRJ-OP-205 | F353: Regulatory Reporting Dashboard | G353: 2026-06-08 | H353: 10 | I353: Billable | J353: Approved

Sheet Capacity Dashboard
B2: Resource Capacity & Utilisation
B3: Weekly utilisation per resource. RED = over 100%. The portfolio average hides the peaks.
B5: Resource | C5: Cap | D5: 06-01 | E5: 06-08 | F5: 06-15 | G5: 06-22 | H5: 06-29 | I5: 07-06 | J5: 07-13 | K5: 07-20 | L5: 07-27 | M5: 08-03 | N5: 08-10 | O5: 08-17 | P5: Peak | Q5: Avg
B6: Amara Okafor | C6: 40 | D6: 0.825 | E6: 0.825 | F6: 0.775 | G6: 0.8 | H6: 0.9 | I6: 0.95 | J6: 0.775 | K6: 0.8 | L6: 0.975 | M6: 0.975 | N6: 0.75 | O6: 0.8 | P6: =MAX(D6:O6) -> 0.975 | Q6: =AVERAGE(D6:O6) -> 0.84583333
B7: Ben Carrow | C7: 40 | D7: 1.575 | E7: 0.725 | F7: 0.85 | G7: 0.8 | H7: 0.725 | I7: 0.7 | J7: 0.7 | K7: 0.825 | L7: 0.85 | M7: 0.725 | N7: 0.725 | O7: 0.825 | P7: =MAX(D7:O7) -> 1.575 | Q7: =AVERAGE(D7:O7) -> 0.83541667
B8: Priya Nair | C8: 40 | D8: 0.8 | E8: 0.825 | F8: 0.9 | G8: 1.4 | H8: 1.4 | I8: 1.4 | J8: 0.95 | K8: 0.75 | L8: 0.775 | M8: 0.725 | N8: 0.725 | O8: 0.95 | P8: =MAX(D8:O8) -> 1.4 | Q8: =AVERAGE(D8:O8) -> 0.96666667
B9: Daniel Kim | C9: 40 | D9: 0.75 | E9: 0.875 | F9: 0.75 | G9: 0.95 | H9: 0.8 | I9: 0.8 | J9: 0.75 | K9: 0.9 | L9: 0.95 | M9: 0.725 | N9: 0.85 | O9: 0.725 | P9: =MAX(D9:O9) -> 0.95 | Q9: =AVERAGE(D9:O9) -> 0.81875
B10: Sofia Rossi | C10: 40 | D10: 0.8 | E10: 0.7 | F10: 0.875 | G10: 0.7 | H10: 0.825 | I10: 0.825 | J10: 0.925 | K10: 0.725 | L10: 0.775 | M10: 0.925 | N10: 0.95 | O10: 0.95 | P10: =MAX(D10:O10) -> 0.95 | Q10: =AVERAGE(D10:O10) -> 0.83125
B11: Marcus Bell | C11: 40 | D11: 0.925 | E11: 0.925 | F11: 0.8 | G11: 0.8 | H11: 0.75 | I11: 0.95 | J11: 0.95 | K11: 0.925 | L11: 0.875 | M11: 0.825 | N11: 0.85 | O11: 0.975 | P11: =MAX(D11:O11) -> 0.975 | Q11: =AVERAGE(D11:O11) -> 0.87916667
B12: Lena Fischer | C12: 40 | D12: 0.8 | E12: 0.925 | F12: 0.9 | G12: 0.85 | H12: 0.725 | I12: 0.95 | J12: 0.85 | K12: 0.875 | L12: 0.8 | M12: 1 | N12: 0.725 | O12: 0.875 | P12: =MAX(D12:O12) -> 1 | Q12: =AVERAGE(D12:O12) -> 0.85625
B13: Tomas Vega | C13: 40 | D13: 0.825 | E13: 0.7 | F13: 0.875 | G13: 0.775 | H13: 0.875 | I13: 0.8 | J13: 0.8 | K13: 0.825 | L13: 0.85 | M13: 0.9 | N13: 0.8 | O13: 0.925 | P13: =MAX(D13:O13) -> 0.925 | Q13: =AVERAGE(D13:O13) -> 0.82916667
B14: Hannah Wright | C14: 40 | D14: 0.85 | E14: 0.9 | F14: 0.8 | G14: 0.725 | H14: 0.825 | I14: 0.95 | J14: 0.9 | K14: 0.925 | L14: 0.875 | M14: 0.725 | N14: 0.8 | O14: 0.775 | P14: =MAX(D14:O14) -> 0.95 | Q14: =AVERAGE(D14:O14) -> 0.8375
B15: Ravi Menon | C15: 32 | D15: 0.781 | E15: 0.844 | F15: 0.781 | G15: 0.844 | H15: 0.906 | I15: 0.719 | J15: 0.969 | K15: 1.25 | L15: 1.25 | M15: 0.938 | N15: 0.906 | O15: 0.938 | P15: =MAX(D15:O15) -> 1.25 | Q15: =AVERAGE(D15:O15) -> 0.92716667
B16: Grace Liu | C16: 40 | D16: 0.95 | E16: 0.975 | F16: 0.7 | G16: 0.925 | H16: 0.85 | I16: 0.925 | J16: 0.975 | K16: 0.75 | L16: 0.975 | M16: 0.825 | N16: 0.75 | O16: 0.95 | P16: =MAX(D16:O16) -> 0.975 | Q16: =AVERAGE(D16:O16) -> 0.87916667
B17: Omar Haddad | C17: 40 | D17: 0.825 | E17: 0.825 | F17: 0.85 | G17: 0.825 | H17: 0.925 | I17: 0.875 | J17: 0.7 | K17: 0.775 | L17: 0.8 | M17: 0.85 | N17: 0.95 | O17: 0.75 | P17: =MAX(D17:O17) -> 0.95 | Q17: =AVERAGE(D17:O17) -> 0.82916667
... B20: Yuki Tanaka | C20: 24 | D20: 0.875 | E20: 0.833 | F20: 0.833 | G20: 0.833 | H20: 1.583 | I20: 0.792 | J20: 0.75 | K20: 0.833 | L20: 0.958 | M20: 0.75 | N20: 0.75 | O20: 0.75 | P20: =MAX(D20:O20) -> 1.583 | Q20: =AVERAGE(D20:O20) -> 0.87833333
B23: Portfolio avg utilisation | F23: =AVERAGE(Q6:Q20) -> 0.85939444
B24: Resources with a peak week over 100% | F24: =COUNTIF(P6:P20,">1") -> 4
B25: Highest peak on the bench | F25: =MAX(P6:P20) -> 1.583

Sheet Defect Log
B2: Portfolio & Resourcing Defect Log
B3: What the PMO Analyst catches. Every defect carries a quantified consequence.
B5: ID | C5: Type | D5: What was found | E5: Severity | F5: Quantified consequence & action | G5: Status
B6: P-01 | C6: Portfolio — status | D6: Insurance Claims Automation reported COST GREEN by the PM, but forecast at completion is 20.5% over budget. | E6: High | F6: $96,502 over. YTD spend was only +2.7% — the overrun sits entirely in $86,500 of committed contractor extensions the status report ignored. Escalated; recovery plan and contingency request raised. | G6: Resolved
B7: P-02 | C7: Portfolio — status | D7: Retail Bank Mobile App reported GREEN; computed AMBER (6.9% over) with 2 milestones already slipped. | E7: Medium | F7: $24,227 over. Reported position corrected at portfolio board; PM coached on including committed costs. | G7: Resolved
B8: P-03 | C8: Portfolio — schedule | D8: Payments Fraud Model: both remaining milestones slipped twice; production deploy now forecast Jan 2027 — outside the contract year. | E8: High | F8: 42-day slip. Revenue recognition moves to the next financial year. Flagged to Finance and Commercial. | G8: Open
B9: P-04 | C9: Portfolio — benefits | D9: Benefit BEN-07 (branch call volume −10%) quietly dropped in month 4. Never formally closed or re-baselined. | E9: Medium | F9: A promised benefit disappeared with no decision record. Business case no longer matches what will be delivered. Formal closure raised to the sponsor. | G9: Open
B10: P-05 | C10: Portfolio — cost | D10: Wealth Platform running 6% UNDER budget — read as a saving, actually a symptom of slipped delivery. | E10: Medium | F10: Underspend tracks a 4-week milestone slip, not efficiency. Cutover now at risk. Reframed at the board as a schedule issue, not a saving. | G10: Resolved
B11: R-01 | C11: Resourcing | D11: Priya Nair (Senior Dev) booked 56h vs 40h capacity = 140% for 3 consecutive weeks across 3 projects. | E11: High | F11: Burnout risk + 2 fixed-price deadlines at risk. Rebalanced 20h to Daniel Kim; capped at 100%. | G11: Resolved
B12: R-02 | C12: Resourcing | D12: Ravi Menon (32h part-time contract) booked to 40h = 125% for 2 weeks. | E12: High | F12: Contract breach + quality risk. Reduced to 32h; surplus BA demand redistributed. | G12: Resolved
B13: R-03 | C13: Resourcing | D13: Skill mismatch — UX Designer allocated to a data-migration task. | E13: Medium | F13: Rework risk. Reassigned to the Data Migration Specialist. | G13: Resolved
B14: R-04 | C14: Resourcing | D14: Ghost resource: allocation against Resource ID R-3099, not in the resource master. | E14: Medium | F14: 30h of real work shown as covered by a person who doesn't exist. Removed and reassigned. | G14: Resolved
B15: R-05 | C15: Resourcing | D15: 3 allocations left 'Tentative' — never confirmed. | E15: Medium | F15: ~60h of capacity blocked but uncommitted. Power Automate flow now chases tentatives older than 5 days. | G15: Resolved
B16: R-06 | C16: Resourcing | D16: A confirmed allocation posted with blank Booked Hours. | E16: Low | F16: Understated a resource's true load and masked their real utilisation. Corrected. | G16: Resolved
B17: R-07 | C17: Resourcing | D17: Duplicate allocation (same resource/project/week) inflated a week to 158%. | E17: Medium | F17: Double-counted capacity and triggered a false over-allocation alert. De-duplicated. | G17: Resolved

Sheet RAID Log
B2: Portfolio RAID Log
B3: Risks · Assumptions · Issues · Dependencies across the book of work.
B5: ID | C5: Type | D5: Description | E5: Owner | F5: Impact | G5: Mitigation / Response | H5: Status | I5: Raised
B6: I-001 | C6: Issue | D6: Portfolio margin forecast to erode from 26.0% to 15.6% — $228K of unplanned cost. | E6: Delivery Director | F6: High | G6: Driven by committed costs on 4 projects. Recovery plans requested from each PM; contingency drawdown paper to the board. | H6: Open | I6: 2026-08-31
B7: I-002 | C7: Issue | D7: 3 of 6 projects reported Green by their PM but compute Amber or Red once committed costs are included. | E7: PCO | F7: High | G7: Reporting standard changed: committed costs now mandatory in every project status. Portfolio dashboard computes RAG independently of PM self-report. | H7: Resolved | I7: 2026-08-31
B8: I-003 | C8: Issue | D8: Senior developer over-allocated to 140% across 2 fixed-price go-lives. | E8: Resourcing Manager | F8: High | G8: Rebalanced within the bench; capped at 100%. See R-01. | H8: Resolved | I8: 2026-06-15
B9: R-001 | C9: Risk | D9: Only 2 senior developers on the bench for 6 projects — single point of failure. | E9: Delivery Director | F9: High | G9: Cross-skilling plan for 2 mid-level developers; contractor pre-approved as surge cover. | H9: Open | I9: 2026-02-20
B10: R-002 | C10: Risk | D10: Payments Fraud deploy forecast into Jan 2027 — revenue recognition slips a financial year. | E10: Finance Business Partner | F10: High | G10: Flagged to Finance and Commercial; recovery options under review. | H10: Open | I10: 2026-08-14
B11: R-003 | C11: Risk | D11: Poor allocation data quality hides true capacity. | E11: PCO | F11: Medium | G11: Weekly data-quality check; automated chase on unconfirmed bookings. See R-04..R-07. | H11: Mitigated | I11: 2026-03-01
B12: A-001 | C12: Assumption | D12: Contracted capacity in the resource master is accurate, including part-timers. | E12: Resourcing Manager | F12: Medium | G12: Verified against HR contracts at kickoff; re-checked quarterly. | H12: Open | I12: 2026-02-02
B13: D-001 | C13: Dependency | D13: Portfolio reporting depends on all 6 PMs submitting status by Wednesday 12:00. | E13: Project Managers | F13: High | G13: Built into the reporting cadence; late submissions escalated to the Delivery Director. | H13: Open | I13: 2026-02-05

Sheet Decision Log
B2: Decision Log
B3: What was decided, by whom, and why.
B5: ID | C5: Date | D5: Decision | E5: Decided by | F5: Rationale
B6: DEC-01 | C6: 2026-08-31 | D6: Report the portfolio AMBER despite 5 of 6 projects being reported Green or Amber by their PMs. | E6: Delivery Director / PCO | F6: Every project looked acceptable on year-to-date spend. Once $177K of committed cost was included, forecast margin fell from 26.0% to 15.6%. Reporting the PMs' aggregated view would have been accurate to what was submitted and completely misleading about where the portfolio lands.
B7: DEC-02 | C7: 2026-08-31 | D7: Change the reporting standard: committed cost is now mandatory in every project status submission, and the portfolio RAG is computed centrally, not self-reported. | E7: Delivery Director | F7: Three PMs reported Green on projects forecasting over budget — not dishonesty, but a status template that only asked for spend to date. Fix the template, not the people.
B8: DEC-03 | C8: 2026-06-15 | D8: Cap the over-allocated senior developer at 100% and move 20h/wk to a mid-level developer, accepting a minor slip on a lower-priority T&M project. | E8: Delivery Director / PCO | F8: A developer at 140% for three weeks will either burn out or ship defects. Both cost more than a small slip on the least critical project.
B9: DEC-04 | C9: 2026-08-14 | D9: Escalate the Payments Fraud go-live slip to Finance rather than absorb it in the delivery plan. | E9: PCO | F9: The deploy now forecasts into January 2027, which moves revenue recognition into the next financial year. That is a Finance decision, not a delivery one.

Sheet Governance Standards
B2: Portfolio Governance Standards
B3: The cadence, thresholds and data rules the PMO runs to. This is the operating manual, not a report.
B5: REPORTING CADENCE
B6: Forum | C6: Frequency | D6: Attendees | E6: Input due | F6: Output
B7: Project status submission | C7: Weekly, Wed 12:00 | D7: All 6 PMs | E7: Wed 12:00 | F7: Status per project incl. committed cost
B8: Resource Review Board | C8: Weekly, Thu 10:00 | D8: Resourcing Mgr, PMs, PCO | E8: Wed EOD | F8: Allocation changes, over-allocation cleared
B9: Portfolio Board | C9: Monthly, 1st Tue | D9: Delivery Director, Finance, PMs | E9: Prior Fri | F9: Portfolio dashboard, decisions, escalations
B10: Benefits review | C10: Quarterly | D10: Sponsor, Business owners | E10: 2 wks prior | F10: Benefits register updated and re-baselined
B12: RAG THRESHOLDS — computed, not self-assessed
B13: Measure | C13: Green | D13: Amber | E13: Red
B14: Cost variance at completion | C14: Within −2% of budget | D14: −2% to −10% | E14: Worse than −10%
B15: Milestone slip | C15: ≤5 days | D15: 6–20 days | E15: Over 20 days
B16: Resource utilisation | C16: 75–85% | D16: 85–90% or 60–75% | E16: Over 90% or under 60%
B17: Benefit tracking | C17: On target | D17: Within 25% of target | E17: Missed or dropped
B19: DATA QUALITY RULES
B20: Rule | C20: Why | D20: Check frequency
B21: Committed cost must be included in every status | C21: Spend to date alone hides forecast overruns — this is how 3 projects reported Green while forecasting over | D21: Weekly
B22: No resource booked above 100% of contracted capacity | C22: Sustained over-booking causes burnout, attrition and defects | D22: Weekly
B23: Tentative bookings older than 5 days are chased automatically | C23: Unconfirmed holds block capacity that is actually available | D23: Automated, daily
B24: Every allocation must map to a resource in the master | C24: Ghost resources create phantom capacity | D24: Weekly
B25: A benefit may only be removed by a logged decision | C25: Benefits quietly dropped leave the business case unmatched to delivery | D25: Quarterly

Sheet Portfolio Status Report
B2: Portfolio Status Report
B3: Meridian Digital Consulting · period ending 31 Aug 2026 · for the monthly Portfolio Board
B5: Overall | C5: AMBER
B6: Cost | C6: AMBER
B7: Schedule | C7: AMBER
B8: Resourcing | C8: GREEN
B9: Benefits | C9: AMBER
B11: Headline
B12: • Five of six projects were submitted Green or Amber by their PMs. Computed centrally with committed cost included, three of those are Amber or Red.
B13: • Portfolio margin is forecast to erode from 26.0% to 15.6% — $228,477 of unplanned cost against $2.215M of contracted revenue.
B14: • Reporting the aggregated PM view would have been accurate to what was submitted, and misleading about where this portfolio lands.
B16: Cost position
B17: • Cost budget $1,640,000 · actual to date $1,448,626 · committed $177,000 · forecast at completion $1,868,477.
B18: • Worst variance: Insurance Claims Automation — +2.7% on year-to-date spend, but 20.5% ($96,502) over at completion once contractor extensions are counted.
B19: • Wealth Platform is 6% under budget — this is a slipped-delivery symptom, not a saving. Reframed as a schedule issue.
B21: Delivery
B22: • 7 milestones at risk across the portfolio; worst slip 42 days.
B23: • Payments Fraud production deploy now forecasts January 2027 — outside the contract year. Escalated to Finance (R-002).
B25: Resourcing
... B32: • NOTE the Payments Fraud revenue-recognition slip into FY2027 and confirm the Finance treatment.
